stream/__init__.py
stream/booleans.py
stream/numbers.py
stream/stream.py
stream/util/__init__.py
stream/util/iterators.py
stream/util/optional.py
java_stream-1.5.1.dist-info/LICENSE
java_stream-1.5.1.dist-info/METADATA
java_stream-1.5.1.dist-info/WHEEL
java_stream-1.5.1.dist-info/top_level.txt
java_stream-1.5.1.dist-info/RECORD
