Metadata-Version: 2.1
Name: java-stream
Version: 1.5.1
Summary: Java Stream implementation for Python
Home-page: https://github.com/alemazzo/Python-Java-Stream
Author: Alessandro Mazzoli
Author-email: developer.alessandro.mazzoli@gmail.com
License: GNU
Keywords: query,iterator,generator,stream,data,functional,list,processing,java,filter,map,reduce,processing
Platform: UNKNOWN
